random_shapes/__init__.py
random_shapes/helper.py
random_shapes/points.py
random_shapes/py.typed
random_shapes/shape.py
random_shapes-0.1.0.dist-info/METADATA
random_shapes-0.1.0.dist-info/WHEEL
random_shapes-0.1.0.dist-info/licenses/LICENSE
random_shapes-0.1.0.dist-info/RECORD
