Metadata-Version: 2.4
Name: random-shapes
Version: 0.1.0
Summary: Generate random shapes with ease.
Project-URL: Documentation, https://relativityhd.github.io/random-shapes/
Project-URL: Repository, https://github.com/relativityhd/random-shapes
Project-URL: Issues, https://github.com/relativityhd/random-shapes/issues
Author-email: Tobias Hölzer <tobiashoelzer@hotmail.com>
License-Expression: GPL-3.0-or-later
License-File: LICENSE
Classifier: Operating System :: OS Independent
Classifier: Programming Language :: Python :: 3
Requires-Python: >=3.11
Requires-Dist: bezier>=2024.6.20
Requires-Dist: opencv-python>=4.11.0.86
Requires-Dist: scipy>=1.15.1
Provides-Extra: viz
Requires-Dist: matplotlib>=3.10.0; extra == 'viz'
